mtei2bangla/__init__.py
mtei2bangla/mtei.py
meiteitobangla-1.1.1.dist-info/LICENCE.md
meiteitobangla-1.1.1.dist-info/METADATA
meiteitobangla-1.1.1.dist-info/WHEEL
meiteitobangla-1.1.1.dist-info/top_level.txt
meiteitobangla-1.1.1.dist-info/RECORD
