Metadata-Version: 2.1
Name: meiteitobangla
Version: 1.1.1
Summary: A package to transliterate from mni-Mtei to mni-Beng
Author: Nokib Sarkar
Project-URL: Homepage, https://github.com/nokibsarkar/meiteitobangla
Project-URL: Issues, https://github.com/nokibsarkar/meiteitobangla/issues
Classifier: Programming Language :: Python :: 3
Classifier: Natural Language :: Bengali
Classifier: Topic :: Text Processing :: Linguistic
Classifier: Operating System :: OS Independent
Classifier: Programming Language :: Python :: 3.10
Requires-Python: >=3.10
License-File: LICENCE.md
